{
  "sections": {
    "hero": {
      "type": "hero-banner",
      "blocks": {
        "slide_1": {
          "type": "slide",
          "settings": {
            "heading": "Spring Collection",
            "subheading": "New Season",
            "button_label": "Shop Now",
            "button_link": "shopify://collections/all",
            "show_overlay": true
          }
        }
      },
      "block_order": ["slide_1"],
      "settings": {}
    },
    "featured": {
      "type": "featured-collection",
      "settings": {
        "heading": "New Arrivals",
        "subheading": "Just In",
        "products_count": 8,
        "show_vendor": false,
        "show_secondary_image": true,
        "show_quick_add": true,
        "show_view_all": true
      }
    }
  },
  "order": [
    "hero",
    "featured"
  ]
}
